musicli/.ruff_cache/.gitignore
musicli/.ruff_cache/CACHEDIR.TAG
musicli/.ruff_cache/content/1476d7b2de80129e
musicli/.ruff_cache/content/2ad51bf6f3d5ad3b
musicli/albums.json
musicli/musicli.py
musicli/THE WEEKND RANKED.png
musicli-0.0.14.dist-info/entry_points.txt
musicli-0.0.14.dist-info/WHEEL
musicli-0.0.14.dist-info/METADATA
musicli-0.0.14.dist-info/RECORD
