Metadata-Version: 2.1
Name: musicli
Version: 0.0.14
Summary: Rate, review, and catalogue all your artists and albums from the command line
Home-page: https://HighnessAtharva.github.io/musicli
License: MIT
Author: Atharva Shah
Author-email: highnessatharva@gmail.com
Requires-Python: >=3.7.1,<4.0
Classifier: Development Status :: 4 - Beta
Classifier: Intended Audience :: Developers
Classifier: License :: OSI Approved :: MIT License
Classifier: Operating System :: OS Independent
Classifier: Programming Language :: Python
Classifier: Programming Language :: Python :: 3
Classifier: Programming Language :: Python :: 3.8
Classifier: Programming Language :: Python :: 3.9
Classifier: Programming Language :: Python :: 3.10
Classifier: Programming Language :: Python :: 3.11
Classifier: Programming Language :: Python :: 3
Classifier: Programming Language :: Python :: 3.7
Classifier: Programming Language :: Python :: 3.8
Classifier: Programming Language :: Python :: 3.9
Classifier: Topic :: Software Development :: Libraries :: Python Modules
Classifier: Typing :: Typed
Requires-Dist: pick (>=2.2.0,<3.0.0)
Requires-Dist: pillow (>=9.5.0,<10.0.0)
Requires-Dist: pylast (>=5.1.0,<6.0.0)
Requires-Dist: rich (>=13.3.4,<14.0.0)
Project-URL: Documentation, https://HighnessAtharva.github.io/musicli
Project-URL: Repository, https://github.com/HighnessAtharva/musicli
